{
  "Daten": [
    {
      "Land": "Gabun",
      "Städte": [
        {
          "Hauptstadt": "Libreville",
          "Bedeutende historische und architektonische Wahrzeichen": "Sankt-Michaels-Kirche mit ihren geschnitzten Holzsäulen, der moderne Präsidentenpalast.",
          "Wichtigste touristische Aktivitäten und Erlebnisse": "Spaziergänge entlang der friedlichen Uferpromenade, Besuch des gabunischen Museums für Kunst und Traditionen, Einkaufen auf dem belebten Mont-Bouët-Markt.",
          "Grünflächen und Landschaften": "Der kleine Bonsuang-Park in der Stadt, die abgelegenen Strände der Stadt.",
          "Berühmte lokale Gerichte": "Nyembwe (Huhn in Palmnusssoße) mit gekochten Kochbananen, frischer gegrillter Fisch am Strand."
        },
        {
          "Hauptstadt": "Port-Gentil",
          "Bedeutende historische und architektonische Wahrzeichen": "Sankt-Louis-Kathedrale, das koloniale Stadtzentrum.",
          "Wichtigste touristische Aktivitäten und Erlebnisse": "Genießen des Strandes L'Escale, Delfinbeobachtungstouren, Angeln im Atlantischen Ozean.",
          "Grünflächen und Landschaften": "Mangrovenwälder um die Stadt, die Bucht von Ogooué.",
          "Berühmte lokale Gerichte": "Frische Austern und gewürzter Karpfen, frittierte Maniokkuchen."
        },
        {
          "Hauptstadt": "Franceville",
          "Bedeutende historische und architektonische Wahrzeichen": "Alte Regierungsgebäude, der zentrale Markt.",
          "Wichtigste touristische Aktivitäten und Erlebnisse": "Besuch der Omar-Bongo-Statue, Erkundung des Hochlandes der Region Haut-Ogooué, Wandern auf Waldwegen.",
          "Grünflächen und Landschaften": "Monda-Park mit seinen offenen Aussichten, die umliegenden grünen Hügel.",
          "Berühmte lokale Gerichte": "Geräuchertes Fleisch (besonders Wild) mit Kürbiskernsoße."
        },
        {
          "Hauptstadt": "Oyem",
          "Bedeutende historische und architektonische Wahrzeichen": "Traditionelle kleine Kirchen, rustikale Holzhäuser.",
          "Wichtigste touristische Aktivitäten und Erlebnisse": "Erfahrung der lokalen Fang-Kultur, Besuch des Marktes für frische landwirtschaftliche Produkte.",
          "Grünflächen und Landschaften": "Waldgebiete nahe der Grenzen zu Kamerun und Äquatorialguinea.",
          "Berühmte lokale Gerichte": "Gekochte Erdnüsse mit Reis, süße gegrillte Bananen."
        },
        {
          "Hauptstadt": "Lambaréné",
          "Bedeutende historische und architektonische Wahrzeichen": "Albert-Schweitzer-Krankenhaus (ein wichtiger historischer medizinischer Ort), Häuser am Flussufer.",
          "Wichtigste touristische Aktivitäten und Erlebnisse": "Historische Tour durch das Albert-Schweitzer-Krankenhaus, Bootsfahrten auf dem Ogooué-See.",
          "Grünflächen und Landschaften": "Das verbundene Seensystem um die Stadt, der botanische Garten des Krankenhauses.",
          "Berühmte lokale Gerichte": "Fluss-Tilapia, Odika-Gemüse-Eintopf."
        },
        {
          "Hauptstadt": "Moanda",
          "Bedeutende historische und architektonische Wahrzeichen": "Überreste alter Minen (Industrietourismus).",
          "Wichtigste touristische Aktivitäten und Erlebnisse": "Besuch des Mangan-Bergbaukomplexes, Erkundung der umliegenden Hügel und Dörfer.",
          "Grünflächen und Landschaften": "Grasbewachsene Hügelsavanne.",
          "Berühmte lokale Gerichte": "Afrikanischer Gemüse-Eintopf mit Huhn, gekochter Maniok."
        },
        {
          "Hauptstadt": "Tchibanga",
          "Bedeutende historische und architektonische Wahrzeichen": "Traditionelle Gebäude des Bunu-Stammes.",
          "Wichtigste touristische Aktivitäten und Erlebnisse": "Besuch der Ibinda-Höhlen, Wandern in der Savanne.",
          "Grünflächen und Landschaften": "Ibinda-Höhlen, Savannenwald.",
          "Berühmte lokale Gerichte": "Mokabi-Gericht (gefüllte Bananenblätter), zerdrückte Bananen."
        },
        {
          "Hauptstadt": "Makokou",
          "Bedeutende historische und architektonische Wahrzeichen": "Makokou-Brücke.",
          "Wichtigste touristische Aktivitäten und Erlebnisse": "Ausgangspunkt für den Ivindo-Nationalpark, Flussbootfahrten.",
          "Grünflächen und Landschaften": "Ivindo-Fluss, umliegende Regenwälder.",
          "Berühmte lokale Gerichte": "Gewürzter Flussfisch, frische Waldfrüchte."
        },
        {
          "Hauptstadt": "Koulamoutou",
          "Bedeutende historische und architektonische Wahrzeichen": "Koulamoutou-Markt.",
          "Wichtigste touristische Aktivitäten und Erlebnisse": "Besuch der nahegelegenen Boundolo-Wasserfälle, Wandern in Bergwäldern.",
          "Grünflächen und Landschaften": "Boundolo-Wasserfälle, Monda-Täler.",
          "Berühmte lokale Gerichte": "Kebondo (Fleisch- und Bohnengericht), Reis mit Gemüse."
        },
        {
          "Hauptstadt": "Gamba",
          "Bedeutende historische und architektonische Wahrzeichen": "Gamba-Forschungsstation.",
          "Wichtigste touristische Aktivitäten und Erlebnisse": "Ökotourismus zur Beobachtung von Elefanten am Strand, Entspannen an den ruhigen Küsten.",
          "Grünflächen und Landschaften": "Loango-Nationalpark (sehr nah), Gamba-See.",
          "Berühmte lokale Gerichte": "Gegrillter Meeresfrüchte, Huhn im Sand vergraben."
        }
      ]
    },
    {
      "Land": "Madagaskar",
      "Städte": [
        {
          "Hauptstadt": "Antananarivo",
          "Bedeutende historische und architektonische Wahrzeichen": "Rova-Palast (Komplex königlicher Paläste), Avenue de l'Indépendance.",
          "Wichtigste touristische Aktivitäten und Erlebnisse": "Erkundung des Königinnenpalastes (Rova), Besuch des Zoma-Marktes, Spaziergänge um den Anosy-See.",
          "Grünflächen und Landschaften": "Lemuren-Park (kurze Entfernung entfernt), Tsimbazaza-Zoo.",
          "Berühmte lokale Gerichte": "Romazava (Fleisch- und Gemüse-Eintopf in Brühe), Ravitoto (Maniokblatt-Eintopf mit Fleisch)."
        },
        {
          "Hauptstadt": "Nosy Be",
          "Bedeutende historische und architektonische Wahrzeichen": "Mount Passot (höchster Punkt), der Leuchtturm Des Sasques.",
          "Wichtigste touristische Aktivitäten und Erlebnisse": "Tauchen und Schnorcheln im Mitsio-Archipel, Angeln im Indischen Ozean, Besuch der Amatovaka-Strände.",
          "Grünflächen und Landschaften": "Bemokoandro-Strand, Lokobe-Nationalpark.",
          "Berühmte lokale Gerichte": "Meeresfrüchte-Curry mit Kokosnuss, frische Ananas."
        },
        {
          "Hauptstadt": "Antsirabe",
          "Bedeutende historische und architektonische Wahrzeichen": "Kathedrale Unserer Lieben Frau von La Salette, der koloniale Bahnhof.",
          "Wichtigste touristische Aktivitäten und Erlebnisse": "Fahren mit traditionellen 'pousse-pousse' Rikschas, Besuch der vulkanischen Seen (Lac Andraikiba), Werkstätten für Handwerk.",
          "Grünflächen und Landschaften": "Andraikiba-See, die Hügel von Antsirabe.",
          "Berühmte lokale Gerichte": "Koba (süßer Reis- und Erdnusskuchen), Bananenkuchen."
        },
        {
          "Hauptstadt": "Morondava",
          "Bedeutende historische und architektonische Wahrzeichen": "Traditionelle Märkte in der Stadt.",
          "Wichtigste touristische Aktivitäten und Erlebnisse": "Besuch der Allee der Baobabs bei Sonnenuntergang, Entspannen am Baobab-Strand.",
          "Grünflächen und Landschaften": "Die berühmte Allee der Baobabs.",
          "Berühmte lokale Gerichte": "Morondavas berühmtes Garnelengericht, Sarimalona (geschmortes Fleisch)."
        },
        {
          "Hauptstadt": "Toliara",
          "Bedeutende historische und architektonische Wahrzeichen": "Das Ethnologische Museum.",
          "Wichtigste touristische Aktivitäten und Erlebnisse": "Besuch des Antsokay-Arboretums, Erkundung der Korallenriffe in der Bucht von Saint-Augustin.",
          "Grünflächen und Landschaften": "Reniala (Pflanzen-) Park, Ifaty-Strand.",
          "Berühmte lokale Gerichte": "Getrockneter Fisch mit Reis, Fischsuppe."
        },
        {
          "Hauptstadt": "Fianarantsoa",
          "Bedeutende historische und architektonische Wahrzeichen": "Alte Stadt Fianarantsoa.",
          "Wichtigste touristische Aktivitäten und Erlebnisse": "Zugfahrt durch den Regenwald, Besuch von Weingärten im Süden.",
          "Grünflächen und Landschaften": "Bergige Landschaftsansichten, Stadtparks.",
          "Berühmte lokale Gerichte": "Lokaler Temoro-Wein, madagassische Pfannkuchen."
        },
        {
          "Hauptstadt": "Mahajanga",
          "Bedeutende historische und architektonische Wahrzeichen": "Mahajanga-Moschee, der Zyklon-Baobab.",
          "Wichtigste touristische Aktivitäten und Erlebnisse": "Genießen des Amborovy-Strandes, Besuch des riesigen Baobab-Baums im Stadtzentrum.",
          "Grünflächen und Landschaften": "Amborovy-Strand, Betsiboka-Fluss.",
          "Berühmte lokale Gerichte": "Masikita (Fleischspieße), Meeresfrüchte."
        },
        {
          "Hauptstadt": "Diego Suarez",
          "Bedeutende historische und architektonische Wahrzeichen": "Leuchtturm von Diego Suarez.",
          "Wichtigste touristische Aktivitäten und Erlebnisse": "Besuch der Buchten von Diego, Genießen der Schönheit des Ramena-Strandes.",
          "Grünflächen und Landschaften": "Die drei Buchten von Diego Suarez, Zuckerhut-Berg.",
          "Berühmte lokale Gerichte": "Gegrillte große Garnelen, Kokosnuss-Fischsuppe."
        },
        {
          "Hauptstadt": "Île Sainte-Marie",
          "Bedeutende historische und architektonische Wahrzeichen": "Historischer Piratenfriedhof.",
          "Wichtigste touristische Aktivitäten und Erlebnisse": "Walbeobachtung (Juli-September), Tauchen in Piratenschiffswracks.",
          "Grünflächen und Landschaften": "Weiße Sandstrände, die Wälder der Insel.",
          "Berühmte lokale Gerichte": "Fisch mit köstlicher Vanillesoße, frische Litschifrüchte."
        },
        {
          "Hauptstadt": "Fort Dauphin",
          "Bedeutende historische und architektonische Wahrzeichen": "Die alte Festung.",
          "Wichtigste touristische Aktivitäten und Erlebnisse": "Surfen an nahegelegenen Stränden, Besuch des Lanano-Sees.",
          "Grünflächen und Landschaften": "Lanano-See, Anosy-Berge.",
          "Berühmte lokale Gerichte": "Langouste (Languste), frische Mango."
        }
      ]
    },
    {
      "Land": "Marokko",
      "Städte": [
        {
          "Hauptstadt": "Marrakesch",
          "Bedeutende historische und architektonische Wahrzeichen": "Platz Djemaa el-Fnaa, Bahia-Palast, Ben-Youssef-Madrasa.",
          "Wichtigste touristische Aktivitäten und Erlebnisse": "Durch die belebte Djemaa el-Fnaa-Platz am Abend schlendern, Besuch des Majorelle-Gartens, Handeln in den Souks der Altstadt.",
          "Grünflächen und Landschaften": "Majorelle-Garten (der blaue Garten), Menara-Gärten, Olivenhain.",
          "Berühmte lokale Gerichte": "Marrakchi Tanjia langsam in einem traditionellen Ofen gegart, Tajine mit Gemüse und Lamm."
        },
        {
          "Hauptstadt": "Casablanca",
          "Bedeutende historische und architektonische Wahrzeichen": "Hassan-II-Moschee (höchster Minarett der Welt), Sacré-Cœur-Kathedrale.",
          "Wichtigste touristische Aktivitäten und Erlebnisse": "Besuch der Hassan-II-Moschee (das Wahrzeichen der Stadt), Spaziergang entlang der Uferpromenade Ain Diab, Erkundung des Habous-Viertels.",
          "Grünflächen und Landschaften": "Uferpromenade Ain Diab, Arabischer Liga-Park.",
          "Berühmte lokale Gerichte": "Traditionelles marokkanisches Couscous, Meeresfrüchtegerichte an der Uferpromenade."
        },
        {
          "Hauptstadt": "Fès",
          "Bedeutende historische und architektonische Wahrzeichen": "Universität Al-Qarawiyyin, traditionelle Gerbereien (Chouara), Bab Boujloud-Tor.",
          "Wichtigste touristische Aktivitäten und Erlebnisse": "Durch das Labyrinth der Altstadt (Fes el-Bali) schlendern, Beobachten der traditionellen Gerbereien, Besuch der Universität Al-Qarawiyyin.",
          "Grünflächen und Landschaften": "Andalusische Gärten, Panoramablick von Borj Fes Nord.",
          "Berühmte lokale Gerichte": "Bastilla (Mandel- und Hühnerpastete), Khlii (konserviertes und getrocknetes Fleisch)."
        },
        {
          "Hauptstadt": "Chefchaouen",
          "Bedeutende historische und architektonische Wahrzeichen": "Platz Outa el Hammam, die Kasbah (alte Festung).",
          "Wichtigste touristische Aktivitäten und Erlebnisse": "Fotografieren der verzauberten blauen Gassen, Einkaufen von Wollhandarbeiten, Wandern zu den Akchour-Wasserfällen.",
          "Grünflächen und Landschaften": "Akchour-Wasserfälle, Talassemtane-Nationalpark.",
          "Berühmte lokale Gerichte": "Frischer lokaler Ziegenkäse, Besara (Saubohnensuppe)."
        },
        {
          "Hauptstadt": "Tanger",
          "Bedeutende historische und architektonische Wahrzeichen": "Kasbah von Tanger, Grand Théâtre.",
          "Wichtigste touristische Aktivitäten und Erlebnisse": "Besuch der Höhlen des Herkules, Beobachten des Zusammentreffens von Mittelmeer und Atlantik am Kap Spartel, Spaziergang in der Kasbah.",
          "Grünflächen und Landschaften": "Höhlen des Herkules, Kap Spartel.",
          "Berühmte lokale Gerichte": "Fischsuppe im nördlichen Stil, Paella (spanischer Einfluss)."
        },
        {
          "Hauptstadt": "Rabat",
          "Bedeutende historische und architektonische Wahrzeichen": "Hassan-Turm, Kasbah der Udayas, Mausoleum Mohammed V.",
          "Wichtigste touristische Aktivitäten und Erlebnisse": "Besuch des Hassan-Turms und des Mausoleums, Spaziergang durch die blau-weiße Kasbah der Udayas, Erkundung der Ruinen von Chellah.",
          "Grünflächen und Landschaften": "Nationaler Zoologischer Garten, Die Exotischen Gärten von Bouknadel.",
          "Berühmte lokale Gerichte": "Rfissa (ein beliebtes Gericht mit Huhn und Linsen), verschiedene marokkanische Gebäcksorten."
        },
        {
          "Hauptstadt": "Agadir",
          "Bedeutende historische und architektonische Wahrzeichen": "Agadir Oufella Kasbah (Panoramablick), Souk El Had.",
          "Wichtigste touristische Aktivitäten und Erlebnisse": "Genießen des großen Agadir-Strandes, Besuch der Agadir Oufella Kasbah, Einkaufen im Souk El Had.",
          "Grünflächen und Landschaften": "Agadir-Strand, Vogeltal.",
          "Berühmte lokale Gerichte": "Frische gegrillte Fischgerichte, Amlou-Öl (Mandeln, Honig und Argan)."
        },
        {
          "Hauptstadt": "Essaouira",
          "Bedeutende historische und architektonische Wahrzeichen": "Befestigungsanlagen von Essaouira, der alte Hafen von Essaouira.",
          "Wichtigste touristische Aktivitäten und Erlebnisse": "Spaziergang in der Medina und dem Hafen, Beobachten des Sonnenuntergangs von den Befestigungsanlagen, Surfen.",
          "Grünflächen und Landschaften": "Essaouira-Strand, Mogador-Inseln.",
          "Berühmte lokale Gerichte": "Gegrillte Sardinen im Hafen, Arganöl-Gerichte."
        },
        {
          "Hauptstadt": "Meknès",
          "Bedeutende historische und architektonische Wahrzeichen": "Bab Mansour (das monumentale Tor), Mausoleum von Moulay Ismail.",
          "Wichtigste touristische Aktivitäten und Erlebnisse": "Besuch von Bab Mansour, Erkundung des Sahrij Swani-Beckens, Tagesausflug zu den römischen Ruinen von Volubilis.",
          "Grünflächen und Landschaften": "Sahrij Swani-Becken, Gärten von Meknès.",
          "Berühmte lokale Gerichte": "Tajine mit eingelegten Oliven und Zitrone, Meknesi-Oliven."
        },
        {
          "Hauptstadt": "Ouarzazate",
          "Bedeutende historische und architektonische Wahrzeichen": "Taourirt Kasbah, Filmstudios (Hollywood Afrikas).",
          "Wichtigste touristische Aktivitäten und Erlebnisse": "Besuch der Filmstudios, Erkundung der Taourirt Kasbah, Ausflug zur Kasbah Aït Benhaddou (UNESCO-Welterbe).",
          "Grünflächen und Landschaften": "Nahegelegene Oasen des Draa-Tals, Ausblicke auf den Hohen Atlas.",
          "Berühmte lokale Gerichte": "Traditionelles Tannour-Brot, Lammgrill."
        }
      ]
    },
    {
      "Land": "Brasilien",
      "Städte": [
        {
          "Hauptstadt": "Rio de Janeiro",
          "Bedeutende historische und architektonische Wahrzeichen": "Christus-Erlöser-Statue, Zuckerhut, das Lapa-Viertel (koloniale Architektur).",
          "Wichtigste touristische Aktivitäten und Erlebnisse": "Besuch des Christus-Erlösers, Fahrt mit der Seilbahn auf den Zuckerhut, Entspannen am Strand von Copacabana.",
          "Grünflächen und Landschaften": "Strände von Copacabana und Ipanema, Nationalpark Tijuca (ein Regenwald innerhalb der Stadt).",
          "Berühmte lokale Gerichte": "Feijoada (Schwarze-Bohnen-Eintopf), der klassische Caipirinha-Cocktail."
        },
        {
          "Hauptstadt": "São Paulo",
          "Bedeutende historische und architektonische Wahrzeichen": "São Paulo Panoramagebäude, São Paulo Kathedrale.",
          "Wichtigste touristische Aktivitäten und Erlebnisse": "Besuch des Kunstmuseums (MASP), Spaziergang entlang der Avenida Paulista, Besuch einer Show im Municipal-Theater.",
          "Grünflächen und Landschaften": "Ibirapuera-Park, Botanischer Garten.",
          "Berühmte lokale Gerichte": "Brasilianische Pizza (dicker Teig), das riesige Mortadella-Sandwich auf dem lokalen Markt."
        },
        {
          "Hauptstadt": "Salvador",
          "Bedeutende historische und architektonische Wahrzeichen": "Das farbenfrohe historische Pelourinho-Viertel (UNESCO-Welterbe), Lacerda-Aufzug.",
          "Wichtigste touristische Aktivitäten und Erlebnisse": "Erkundung des farbenfrohen historischen Pelourinho-Viertels, Beobachten von Capoeira-Shows, Fahrt mit dem Lacerda-Aufzug.",
          "Grünflächen und Landschaften": "Strände von Porto da Barra, See Atrassão.",
          "Berühmte lokale Gerichte": "Acarajé (frittierter Bohnenkuchen), Moqueca (Fisch-Kokos-Eintopf)."
        },
        {
          "Hauptstadt": "Foz do Iguaçu",
          "Bedeutende historische und architektonische Wahrzeichen": "Itaipu-Staudamm (einer der größten Staudämme der Welt).",
          "Wichtigste touristische Aktivitäten und Erlebnisse": "Erkundung der Iguaçu-Wasserfälle von der brasilianischen Seite, Besuch des Vogelparks (Parque das Aves).",
          "Grünflächen und Landschaften": "Nationalpark Iguaçu, der Vogelpark.",
          "Berühmte lokale Gerichte": "Gegrillter Dourado-Fisch, Churrasco (Grillfest)."
        },
        {
          "Hauptstadt": "Manaus",
          "Bedeutende historische und architektonische Wahrzeichen": "Amazonas-Theater, Adolfo Lisboa Markt.",
          "Wichtigste touristische Aktivitäten und Erlebnisse": "Bootfahrten im Amazonas-Regenwald, Zeuge des Zusammentreffens der Gewässer (Flüsse Negro und Solimões), Besuch des Amazonas-Theaters.",
          "Grünflächen und Landschaften": "Das Zusammentreffen der Gewässer, nahegelegene Amazonas-Reservate.",
          "Berühmte lokale Gerichte": "Gegrillter Tambaqui-Fisch, Tacacá-Suppe (Garnelen mit Maniok)."
        },
        {
          "Hauptstadt": "Brasília",
          "Bedeutende historische und architektonische Wahrzeichen": "Brasília-Kathedrale, Gebäude des Nationalkongresses.",
          "Wichtigste touristische Aktivitäten und Erlebnisse": "Besuch der weltraumähnlichen Brasília-Kathedrale, Spaziergang um den Platz der Drei Gewalten, Besuch der Juscelino-Kubitschek-Brücke.",
          "Grünflächen und Landschaften": "Paranoá-See, Nationalpark Brasília.",
          "Berühmte lokale Gerichte": "Grillfest (Churrasco), Gerichte der Mittelwestregion."
        },
        {
          "Hauptstadt": "Recife",
          "Bedeutende historische und architektonische Wahrzeichen": "Historische Stadt Olinda (nahe Recife), Kulturzentrum Cais do Sertão.",
          "Wichtigste touristische Aktivitäten und Erlebnisse": "Erkundung der Altstadt (Recife Antigo), Genuss des Strandes Boa Viagem, Besuch von Handwerkswerkstätten.",
          "Grünflächen und Landschaften": "Strand Boa Viagem, Capibaribe-Fluss.",
          "Berühmte lokale Gerichte": "Bolo de Rolo (lokaler Kuchen), Meeresfisch."
        },
        {
          "Hauptstadt": "Florianópolis",
          "Bedeutende historische und architektonische Wahrzeichen": "Hercílio-Luz-Brücke.",
          "Wichtigste touristische Aktivitäten und Erlebnisse": "Surfen am Strand Praia Mole, Sandboarding an der Joaquina.",
          "Grünflächen und Landschaften": "Lagoa da Conceição Lagune, Campeche-Strand.",
          "Berühmte lokale Gerichte": "Frische Austern (das Hauptgericht), frische Mango."
        },
        {
          "Hauptstadt": "Gramado",
          "Bedeutende historische und architektonische Wahrzeichen": "São Pedro Kirche.",
          "Wichtigste touristische Aktivitäten und Erlebnisse": "Besuch von Snowland, Spaziergang um den Negro-See, Probieren von handgemachten Schokoladen.",
          "Grünflächen und Landschaften": "Negro-See, Mini Mundo.",
          "Berühmte lokale Gerichte": "Fondue (schweizerischer Einfluss), heiße Schokolade."
        },
        {
          "Hauptstadt": "Fortaleza",
          "Bedeutende historische und architektonische Wahrzeichen": "José-de-Alencar-Theater, Festung Nossa Senhora da Assunção.",
          "Wichtigste touristische Aktivitäten und Erlebnisse": "Genuss des Strandes Futuro, Besuch des Kulturzentrums Dragão do Mar, Einkaufen von Handarbeiten.",
          "Grünflächen und Landschaften": "Strand Futuro, Strand Iracema.",
          "Berühmte lokale Gerichte": "Gegrillter Hummer, Baião de Dois (Reis und Bohnen)."
        }
      ]
    },
    {
      "Land": "Bulgarien",
      "Städte": [
        {
          "Hauptstadt": "Sofia",
          "Bedeutende historische und architektonische Wahrzeichen": "Alexander-Newski-Kathedrale, Sankt-Georgs-Rotunde (die älteste), Banya-Baschi-Moschee.",
          "Wichtigste touristische Aktivitäten und Erlebnisse": "Besuch der Alexander-Newski-Kathedrale, Fahrt mit der Seilbahn auf den Berg Vitosha, Einkaufen in der Vitosha-Straße.",
          "Grünflächen und Landschaften": "Berg Vitosha (leicht erreichbar), Borisova Gradina Park.",
          "Berühmte lokale Gerichte": "Schopska-Salat (Gurke, Tomate, bulgarischer Käse), Banitsa (herzhafter Kuchen)."
        },
        {
          "Hauptstadt": "Plovdiv",
          "Bedeutende historische und architektonische Wahrzeichen": "Altes römisches Theater, die Altstadt, Dzhumaya-Moschee.",
          "Wichtigste touristische Aktivitäten und Erlebnisse": "Besuch des alten römischen Theaters, Spaziergang im künstlerischen Kapana-Viertel, Erkundung der Altstadt.",
          "Grünflächen und Landschaften": "Die Sieben Hügel (einschließlich der Hügel der Stadt), Maritza-Fluss.",
          "Berühmte lokale Gerichte": "Tarator (kalte Joghurtsuppe), Kavarma (Fleischeintopf im Tontopf)."
        },
        {
          "Hauptstadt": "Varna",
          "Bedeutende historische und architektonische Wahrzeichen": "Archäologisches Museum Varna (ältestes Gold der Welt), Kathedrale Entschlafung der Muttergottes.",
          "Wichtigste touristische Aktivitäten und Erlebnisse": "Entspannen am Strand, Besuch des Archäologischen Museums, Spaziergang durch den Seegarten.",
          "Grünflächen und Landschaften": "Der Seegarten, Strände am Schwarzen Meer.",
          "Berühmte lokale Gerichte": "Schwarzes-Meer-Tilapia, Muscheln mit Knoblauch."
        },
        {
          "Hauptstadt": "Burgas",
          "Bedeutende historische und architektonische Wahrzeichen": "Seegarten Burgas, Heilig-Heilige-Kirche.",
          "Wichtigste touristische Aktivitäten und Erlebnisse": "Besuch des Sandfestivals (im Sommer), Spaziergang im Seegarten, Besuch des Atanasovsko-Sees zur Vogelbeobachtung.",
          "Grünflächen und Landschaften": "Atanasovsko-See, der Seegarten.",
          "Berühmte lokale Gerichte": "Tsatsa (kleine frittierte Fische), Meeresfrüchtegerichte."
        },
        {
          "Hauptstadt": "Veliko Tarnovo",
          "Bedeutende historische und architektonische Wahrzeichen": "Festung Zarevec, Samovodska Charshia Straße.",
          "Wichtigste touristische Aktivitäten und Erlebnisse": "Besuch der Festung Zarevec, Spaziergang auf der Handwerkerstraße, Beobachten der 'Klang und Licht'-Show nachts.",
          "Grünflächen und Landschaften": "Jantra-Fluss, umliegende Bergansichten.",
          "Berühmte lokale Gerichte": "Schweine- und Kartoffeleintopf, traditionelles Patatnik-Brot."
        },
        {
          "Hauptstadt": "Nesebar",
          "Bedeutende historische und architektonische Wahrzeichen": "Alte byzantinische Kirchen, die alten Festungsmauern.",
          "Wichtigste touristische Aktivitäten und Erlebnisse": "Spaziergang in der alten Halbinsel (UNESCO-Welterbe), Besuch der alten byzantinischen Kirchen.",
          "Grünflächen und Landschaften": "Nahegelegener Sonnenstrand, das Schwarze Meer.",
          "Berühmte lokale Gerichte": "Frische Meeresfrüchte, lokaler Weißwein."
        },
        {
          "Hauptstadt": "Bansko",
          "Bedeutende historische und architektonische Wahrzeichen": "Heilig-Dreifaltigkeits-Kirche, Platz Velio Tarnovo.",
          "Wichtigste touristische Aktivitäten und Erlebnisse": "Skifahren (im Winter), Wandern im Pirin-Gebirge (im Sommer).",
          "Grünflächen und Landschaften": "Nationalpark Pirin-Gebirge, Bansko-See.",
          "Berühmte lokale Gerichte": "Kapama (traditioneller lang gekochter Eintopf), Chomlek (Fleischeintopf im Topf)."
        },
        {
          "Hauptstadt": "Sozopol",
          "Bedeutende historische und architektonische Wahrzeichen": "Historische Holzhäuser, der alte Hafen.",
          "Wichtigste touristische Aktivitäten und Erlebnisse": "Erkundung der alten Holzstadt, Entspannen an ruhigen Stränden.",
          "Grünflächen und Landschaften": "Strände von Sozopol, Insel Sweti Iwan.",
          "Berühmte lokale Gerichte": "Feigenmarmelade (regionale Spezialität), gegrillter Fisch."
        },
        {
          "Hauptstadt": "Ruse",
          "Bedeutende historische und architektonische Wahrzeichen": "Platz der Freiheit, das Neue-Zeit-Gebäude.",
          "Wichtigste touristische Aktivitäten und Erlebnisse": "Spaziergang entlang der Donau, Erkundung der österreichischen Barockarchitektur.",
          "Grünflächen und Landschaften": "Donau-Fluss, Swoboda-Park.",
          "Berühmte lokale Gerichte": "Donau-Fischsuppe, Schweinegerichte."
        },
        {
          "Hauptstadt": "Kazanlak",
          "Bedeutende historische und architektonische Wahrzeichen": "Thrakisches Grab (UNESCO-Welterbe), Rosenmuseum.",
          "Wichtigste touristische Aktivitäten und Erlebnisse": "Besuch des Rosenmuseums, Erkundung thrakischer Gräber, Teilnahme am Rosenfest (Mai-Juni).",
          "Grünflächen und Landschaften": "Das Rosental, das Balkangebirge.",
          "Berühmte lokale Gerichte": "Rosenmarmelade, Rosenlikör."
        }
      ]
    },
    {
      "Land": "Bosnien und Herzegowina",
      "Städte": [
        {
          "Hauptstadt": "Sarajevo",
          "Bedeutende historische und architektonische Wahrzeichen": "Ottomanischer Baščaršija-Markt, Lateinische Brücke, Gazi-Husrev-Beg-Moschee.",
          "Wichtigste touristische Aktivitäten und Erlebnisse": "Durch den osmanischen Baščaršija-Markt schlendern, Besuch der Lateinischen Brücke, Fahrt mit der Seilbahn auf den Berg Trebević.",
          "Grünflächen und Landschaften": "Berg Trebević (mit Seilbahn erreichbar), der Fluss, Vrelo Bosne Park.",
          "Berühmte lokale Gerichte": "Bosnische ćevapi in Somun-Brot, Burek (mit Fleisch oder Käse gefüllte Teigwaren)."
        },
        {
          "Hauptstadt": "Mostar",
          "Bedeutende historische und architektonische Wahrzeichen": "Die Alte Brücke (Stari Most), alte osmanische Häuser.",
          "Wichtigste touristische Aktivitäten und Erlebnisse": "Beobachten von Springern von der Alten Brücke (Stari Most), Erkundung des alten Basars, Besuch des Kriegsmuseums.",
          "Grünflächen und Landschaften": "Der smaragdgrüne Neretva-Fluss, Gärten am Flussufer.",
          "Berühmte lokale Gerichte": "Dolma (gefülltes Gemüse), Tufahija (traditionelles Kürbisdessert)."
        },
        {
          "Hauptstadt": "Banja Luka",
          "Bedeutende historische und architektonische Wahrzeichen": "Festung Kastel, Ferhadija-Moschee.",
          "Wichtigste touristische Aktivitäten und Erlebnisse": "Besuch der Festung Kastel, Rafting auf dem Vrbas-Fluss, Besuch der Ferhadija-Moschee.",
          "Grünflächen und Landschaften": "Vrbas-Fluss, Gärten von Banja Luka.",
          "Berühmte lokale Gerichte": "Banja Luka ćevapi, lokaler Trappista-Käse."
        },
        {
          "Hauptstadt": "Blagaj",
          "Bedeutende historische und architektonische Wahrzeichen": "Das in den Fels gehauene Derwisch-Kloster.",
          "Wichtigste touristische Aktivitäten und Erlebnisse": "Besuch des Derwisch-Klosters, Sehen der Quelle des Buna-Flusses.",
          "Grünflächen und Landschaften": "Die Quelle des Buna-Flusses, die umliegenden Klippen.",
          "Berühmte lokale Gerichte": "Frische Forelle, Kalbsbraten."
        },
        {
          "Hauptstadt": "Trebinje",
          "Bedeutende historische und architektonische Wahrzeichen": "Arslanagić-Brücke, die Altstadt.",
          "Wichtigste touristische Aktivitäten und Erlebnisse": "Spaziergang auf der Arslanagić-Brücke, Besuch des Klosters Hercegovačka Gračanica, Verkostung von lokalem Wein.",
          "Grünflächen und Landschaften": "Trebišnjica-Fluss, Kirche Gračanica (Panoramablick).",
          "Berühmte lokale Gerichte": "Käse in Öl, Pršut (gekochter Schinken)."
        },
        {
          "Hauptstadt": "Jajce",
          "Bedeutende historische und architektonische Wahrzeichen": "Die Königliche Festung, Sankt-Lukas-Kathedrale.",
          "Wichtigste touristische Aktivitäten und Erlebnisse": "Sehen des großen Wasserfalls im Stadtzentrum, Besuch der Königlichen Festung, Erkundung der Wassermühlen.",
          "Grünflächen und Landschaften": "Wasserfall Jajce, Pliva-See, Wassermühlen.",
          "Berühmte lokale Gerichte": "Zeljanica (Käsekuchen), ćevapi."
        },
        {
          "Hauptstadt": "Travnik",
          "Bedeutende historische und architektonische Wahrzeichen": "Die farbenfrohe Festung von Travnik, die farbenfrohe Moschee.",
          "Wichtigste touristische Aktivitäten und Erlebnisse": "Besuch der farbenfrohen Festung von Travnik, Erkundung der farbenfrohen Moschee, Besuch des Hauses von Ivo Andrić.",
          "Grünflächen und Landschaften": "Lašva-Fluss, umliegende Berge.",
          "Berühmte lokale Gerichte": "Vlašić-Käse, Travnik ćevapi."
        },
        {
          "Hauptstadt": "Konjic",
          "Bedeutende historische und architektonische Wahrzeichen": "Titos Atombunker (Ark D-0).",
          "Wichtigste touristische Aktivitäten und Erlebnisse": "Fotos machen an der osmanischen Brücke, Besuch von Titos Atombunker.",
          "Grünflächen und Landschaften": "Neretva-Fluss, raue Berge.",
          "Berühmte lokale Gerichte": "Gegrillter Flussfisch, Maisbrei (bura)."
        },
        {
          "Hauptstadt": "Višegrad",
          "Bedeutende historische und architektonische Wahrzeichen": "Mehmed-Paša-Sokolović-Brücke (UNESCO), Andrićgrad.",
          "Wichtigste touristische Aktivitäten und Erlebnisse": "Spaziergang auf der Mehmed-Paša-Sokolović-Brücke (Drina-Brücke), Besuch von Andrićgrad.",
          "Grünflächen und Landschaften": "Drina-Fluss, umliegende Landschaften.",
          "Berühmte lokale Gerichte": "Drina-Flussfisch, Fleischgerichte."
        },
        {
          "Hauptstadt": "Bihać",
          "Bedeutende historische und architektonische Wahrzeichen": "Kapetanova-Turm, Fethija-Moschee.",
          "Wichtigste touristische Aktivitäten und Erlebnisse": "Rafting auf dem Una-Fluss, Besuch der nahegelegenen Štrbački-Buk-Wasserfälle.",
          "Grünflächen und Landschaften": "Una-Fluss, Nationalpark Una, Štrbački-Buk-Wasserfälle.",
          "Berühmte lokale Gerichte": "Mokapi-Gericht (gefüllte Bananenblätter), zerdrückte Bananen."
        }
      ]
    },
    {
      "Land": "Portugal",
      "Städte": [
        {
          "Hauptstadt": "Lissabon",
          "Bedeutende historische und architektonische Wahrzeichen": "Belém-Turm, Hieronymus-Kloster, Praça do Comércio.",
          "Wichtigste touristische Aktivitäten und Erlebnisse": "Fahrt mit der Straßenbahn 28, Besuch des Belém-Turms, Hören von Fado-Musik im Alfama-Viertel.",
          "Grünflächen und Landschaften": "Eduard-VII-Park, Tejo-Fluss, Panoramablick von den Hügeln.",
          "Berühmte lokale Gerichte": "Pastel de nata (Vanillecremetorte), Bacalhau (Salzkabeljau) in verschiedenen Zubereitungen."
        },
        {
          "Hauptstadt": "Porto",
          "Bedeutende historische und architektonische Wahrzeichen": "Dom-Luís-I-Brücke, Livraria Lello, São-Bento-Station (Azulejo-Fliesen).",
          "Wichtigste touristische Aktivitäten und Erlebnisse": "Verkostung von Portwein in Vila Nova de Gaia, Spaziergang über die Dom-Luís-I-Brücke, Besuch der Livraria Lello.",
          "Grünflächen und Landschaften": "Douro-Fluss, Kristallpalast-Gärten.",
          "Berühmte lokale Gerichte": "Francesinha (mit Käse und Soße bedecktes Sandwich), Tripas (traditionelles Gericht)."
        },
        {
          "Hauptstadt": "Sintra",
          "Bedeutende historische und architektonische Wahrzeichen": "Nationalpalast Pena, Quinta da Regaleira, die Burg der Mauren.",
          "Wichtigste touristische Aktivitäten und Erlebnisse": "Besuch des farbenfrohen Pena-Palastes, Erkundung der mysteriösen Quinta da Regaleira, der alten Burg der Mauren.",
          "Grünflächen und Landschaften": "Sintra-Berge, Gärten der Quinta da Regaleira.",
          "Berühmte lokale Gerichte": "Travesseiros (Mandelgebäck), Queijadas (Käsekuchen)."
        },
        {
          "Hauptstadt": "Faro",
          "Bedeutende historische und architektonische Wahrzeichen": "Igreja do Carmo (Knochenkapelle), das alte Tor von Faro.",
          "Wichtigste touristische Aktivitäten und Erlebnisse": "Erkundung der befestigten Altstadt, Bootsfahrt im Naturpark Ria Formosa.",
          "Grünflächen und Landschaften": "Naturpark Ria Formosa, Strand von Faro.",
          "Berühmte lokale Gerichte": "Cataplana (Meeresfrüchte-Eintopf), gegrillte Sardinen."
        },
        {
          "Hauptstadt": "Lagos",
          "Bedeutende historische und architektonische Wahrzeichen": "Festung Ponta da Bandeira, der alte Sklavenmarkt.",
          "Wichtigste touristische Aktivitäten und Erlebnisse": "Bootstouren zur Erkundung der Höhlen von Ponta da Piedade, Entspannen am Strand Dona Ana.",
          "Grünflächen und Landschaften": "Klippen von Ponta da Piedade, Strand Dona Ana.",
          "Berühmte lokale Gerichte": "Dom Rodrigo (süße Eigelb-Süßigkeiten), Meeresfrüchte."
        },
        {
          "Hauptstadt": "Coimbra",
          "Bedeutende historische und architektonische Wahrzeichen": "Alte Universität Coimbra und ihre Joanina-Bibliothek, Santa-Kreuz-Kloster.",
          "Wichtigste touristische Aktivitäten und Erlebnisse": "Tour durch die alte Universität Coimbra und ihre Joanina-Bibliothek, Hören von Coimbra-Fado.",
          "Grünflächen und Landschaften": "Mondego-Fluss, der Botanische Garten.",
          "Berühmte lokale Gerichte": "Huhn in Soße, Pudim Abade de Priscos."
        },
        {
          "Hauptstadt": "Évora",
          "Bedeutende historische und architektonische Wahrzeichen": "Römischer Tempel der Diana, Knochenkapelle (Capela dos Ossos).",
          "Wichtigste touristische Aktivitäten und Erlebnisse": "Besuch des römischen Tempels der Diana, Erkundung der Knochenkapelle.",
          "Grünflächen und Landschaften": "Umgebende Ebenen des Alentejo, Weinberge.",
          "Berühmte lokale Gerichte": "Açorda (Brotsuppe), schwarzer iberischer Schinken."
        },
        {
          "Hauptstadt": "Aveiro",
          "Bedeutende historische und architektonische Wahrzeichen": "Aveiro-Museum.",
          "Wichtigste touristische Aktivitäten und Erlebnisse": "Fahrt mit farbenfrohen Moliceiro-Booten (das Venedig Portugals), Besuch des gestreiften Strandes (Costa Nova).",
          "Grünflächen und Landschaften": "Die Kanäle der Stadt, Strand Costa Nova.",
          "Berühmte lokale Gerichte": "Ovos Moles (weiche Eier-Süßigkeiten), Meeresfrüchte."
        },
        {
          "Hauptstadt": "Braga",
          "Bedeutende historische und architektonische Wahrzeichen": "Heiligtum Bom Jesus do Monte, Braga-Kathedrale (Sé).",
          "Wichtigste touristische Aktivitäten und Erlebnisse": "Besteigung der Stufen des Heiligtums Bom Jesus, Besuch der Braga-Kathedrale.",
          "Grünflächen und Landschaften": "Gärten von Santa Barbara, die Hügel von Braga.",
          "Berühmte lokale Gerichte": "Huhn in Soße, Pudim Abade de Priscos."
        },
        {
          "Hauptstadt": "Cascais",
          "Bedeutende historische und architektonische Wahrzeichen": "Zitadelle von Cascais, Museu Conde de Castro.",
          "Wichtigste touristische Aktivitäten und Erlebnisse": "Spaziergang im Hafen, Sehen der Klippen Boca do Inferno, Verkostung von handgemachten Schokoladen.",
          "Grünflächen und Landschaften": "Boca do Inferno, Strand Guincho.",
          "Berühmte lokale Gerichte": "Grillfeste, Meeresfrüchte."
        }
      ]
    },
    {
      "Land": "Paraguay",
      "Städte": [
        {
          "Hauptstadt": "Asunción",
          "Bedeutende historische und architektonische Wahrzeichen": "Palacio de los López (Präsidentenpalast), Panteón de los Héroes, Nationalmuseum.",
          "Wichtigste touristische Aktivitäten und Erlebnisse": "Besuch des Palacio de los López, Spaziergang durch den Panteón de los Héroes, Spaziergang entlang der Uferpromenade.",
          "Grünflächen und Landschaften": "Uferpromenade von Asunción am Paraguay-Fluss, der Botanische Garten und Zoo.",
          "Berühmte lokale Gerichte": "Sopa Paraguaya (salziger Maiskuchen), Chipa (Maniok- und Käsebrot)."
        },
        {
          "Hauptstadt": "Ciudad del Este",
          "Bedeutende historische und architektonische Wahrzeichen": "Itaipu-Staudamm (ein massives Ingenieurprojekt).",
          "Wichtigste touristische Aktivitäten und Erlebnisse": "Einkaufen (Grenzhandel), Besuch des Itaipu-Wasserkraftwerks, Sehen der Monday-Wasserfälle.",
          "Grünflächen und Landschaften": "Monday-Wasserfälle, Paraná-Fluss.",
          "Berühmte lokale Gerichte": "Pica-pau (gehacktes und gebratenes Fleisch), Tereré (kalter Mate-Tee)."
        },
        {
          "Hauptstadt": "Encarnación",
          "Bedeutende historische und architektonische Wahrzeichen": "Jesuitenruinen von Trinidad (nahe Encarnación).",
          "Wichtigste touristische Aktivitäten und Erlebnisse": "Spaziergang entlang der Uferpromenade des Paraná-Flusses, Genuss der Flussstrände, Besuch der nahegelegenen Jesuitenruinen.",
          "Grünflächen und Landschaften": "Uferpromenade des Paraná-Flusses, Flussstrände.",
          "Berühmte lokale Gerichte": "Mbeju (Stärke- und Käsepfannkuchen), gefüllte Crêpes."
        },
        {
          "Hauptstadt": "Villarrica",
          "Bedeutende historische und architektonische Wahrzeichen": "Die Kathedrale, Manuel-Ortiz-Museum.",
          "Wichtigste touristische Aktivitäten und Erlebnisse": "Erkundung des Landes und der Yerba-Mate-Plantagen, Fahrt mit alten landwirtschaftlichen Kutschen.",
          "Grünflächen und Landschaften": "Die Hügel der Gegend, landwirtschaftliche Felder.",
          "Berühmte lokale Gerichte": "Vorái (lokales Hühngericht), Butifarra (Rindfleisch)."
        },
        {
          "Hauptstadt": "Concepción",
          "Bedeutende historische und architektonische Wahrzeichen": "Die Hauptkirche, der alte Hafen.",
          "Wichtigste touristische Aktivitäten und Erlebnisse": "Tour durch den alten Hafen, Bootsfahrten auf dem Paraguay-Fluss, Erkundung kolonialer Gebäude.",
          "Grünflächen und Landschaften": "Paraguay-Fluss, Parks am Flussufer.",
          "Berühmte lokale Gerichte": "Gegrillter Flussfisch, Fischsuppe."
        },
        {
          "Hauptstadt": "Areguá",
          "Bedeutende historische und architektonische Wahrzeichen": "San-Lorenzo-Kirche.",
          "Wichtigste touristische Aktivitäten und Erlebnisse": "Besuch des Ypacaraí-Sees (Panoramablick), der Töpferei- und Handwerksmarkt.",
          "Grünflächen und Landschaften": "Ypacaraí-See, Cerro Kõi-Park.",
          "Berühmte lokale Gerichte": "Erdbeeren mit Sahne (saisonal), Chipa-Gericht."
        },
        {
          "Hauptstadt": "Caacupé",
          "Bedeutende historische und architektonische Wahrzeichen": "Basilika Unserer Lieben Frau der Wunder.",
          "Wichtigste touristische Aktivitäten und Erlebnisse": "Besteigung der umliegenden Hügel, Besuch der Kathedrale (ein Wallfahrtsort).",
          "Grünflächen und Landschaften": "Hügel von Cerro Caacupé, Landschaftsfarmen.",
          "Berühmte lokale Gerichte": "Traditionelle Süßigkeiten, Maiskuchen."
        },
        {
          "Hauptstadt": "San Bernardino",
          "Bedeutende historische und architektonische Wahrzeichen": "Alte Sommerhäuser.",
          "Wichtigste touristische Aktivitäten und Erlebnisse": "Genuss von Wassersport auf dem Ypacaraí-See, Zeit im Badeort verbringen.",
          "Grünflächen und Landschaften": "Ypacaraí-See.",
          "Berühmte lokale Gerichte": "Grillfeste, internationale Küche."
        },
        {
          "Hauptstadt": "Filadelfia",
          "Bedeutende historische und architektonische Wahrzeichen": "Museum der Mennoniten-Kolonien.",
          "Wichtigste touristische Aktivitäten und Erlebnisse": "Besuch des Museums der Mennoniten-Kolonien, Erkundung der Chaco-Ebenen.",
          "Grünflächen und Landschaften": "Die trockene Chaco-Region.",
          "Berühmte lokale Gerichte": "Mennoniten-Käse und Molkereiprodukte, geräuchertes Fleisch."
        },
        {
          "Hauptstadt": "Yaguarón",
          "Bedeutende historische und architektonische Wahrzeichen": "Yaguarón-Kirche (ein Holz-Meisterwerk).",
          "Wichtigste touristische Aktivitäten und Erlebnisse": "Besuch der alten Franziskanerkirche, Besteigung des Yaguarón-Hügels.",
          "Grünflächen und Landschaften": "Yaguarón-Hügel.",
          "Berühmte lokale Gerichte": "Caracú (Schnecken)-Gericht, ländliche Gerichte."
        }
      ]
    },
    {
      "Land": "Weißrussland",
      "Städte": [
        {
          "Hauptstadt": "Minsk",
          "Bedeutende historische und architektonische Wahrzeichen": "Nationalbibliothek (diamantförmige Architektur), Siegesplatz, Kathedrale des Heiligen Geistes.",
          "Wichtigste touristische Aktivitäten und Erlebnisse": "Besuch der Insel der Tränen und des Swislatsch-Flusses, Erkundung der langen Unabhängigkeitsallee, Besuch der Nationalbibliothek.",
          "Grünflächen und Landschaften": "Gorki-Park, Swislatsch-Fluss, Insel der Tränen.",
          "Berühmte lokale Gerichte": "Dranki (Kartoffelpuffer), weißrussische Borschtsch-Suppe."
        },
        {
          "Hauptstadt": "Brest",
          "Bedeutende historische und architektonische Wahrzeichen": "Festung Brest, Fußgängerzone Sowetskaja-Straße.",
          "Wichtigste touristische Aktivitäten und Erlebnisse": "Besuch der Festung Brest, Spaziergang durch die laterne beleuchtete Straße bei Nacht, Besuch des Archäologischen Museums.",
          "Grünflächen und Landschaften": "Bug-Fluss, Nationalpark Brest.",
          "Berühmte lokale Gerichte": "Weißrussisch mariniertes Huhn, das beliebte Kwass-Getränk."
        },
        {
          "Hauptstadt": "Grodno",
          "Bedeutende historische und architektonische Wahrzeichen": "Die Alte und Neue Burg, Kaloscha-Kirche.",
          "Wichtigste touristische Aktivitäten und Erlebnisse": "Besuch der Alten und Neuen Burg, Erkundung historischer Kirchen, Spaziergang entlang des Neman-Flusses.",
          "Grünflächen und Landschaften": "Neman-Fluss, Gilibert-Park.",
          "Berühmte lokale Gerichte": "Mit Fleisch gefüllte Teigtaschen (Pelmeni), Kartoffeln mit Fleisch."
        },
        {
          "Hauptstadt": "Wizebsk",
          "Bedeutende historische und architektonische Wahrzeichen": "Marc-Chagall-Museum (der berühmte Maler), die Sommer-Arena.",
          "Wichtigste touristische Aktivitäten und Erlebnisse": "Besuch des Marc-Chagall-Museums, Teilnahme am Slawianski-Bazar-Kunstfestival.",
          "Grünflächen und Landschaften": "Dwina-Fluss, Park Wizebsk.",
          "Berühmte lokale Gerichte": "Heringsalat (Selyodka) mit Gemüse, Reis- und Pilzgericht."
        },
        {
          "Hauptstadt": "Homel",
          "Bedeutende historische und architektonische Wahrzeichen": "Rumjanzew-Paschkewitsch-Palast (Museum und Park), St. Peter und Paul Kathedrale.",
          "Wichtigste touristische Aktivitäten und Erlebnisse": "Besuch des Rumjanzew-Paschkewitsch-Palastes, Spaziergang entlang des Sozh-Flusses.",
          "Grünflächen und Landschaften": "Sozh-Fluss, der Palastpark.",
          "Berühmte lokale Gerichte": "Gefüllte Kuchen (Piroshki), eingelegtes Schweinefleisch."
        },
        {
          "Hauptstadt": "Mahiljou",
          "Bedeutende historische und architektonische Wahrzeichen": "Rathaus von Mahiljou.",
          "Wichtigste touristische Aktivitäten und Erlebnisse": "Besuch des alten Rathauses, Erkundung des Sternenplatzes, Spaziergang im Zoo.",
          "Grünflächen und Landschaften": "Dnjepr-Fluss, Park Mahiljou.",
          "Berühmte lokale Gerichte": "Gebratenes Schweinefleisch mit Kartoffeln, einfache Gerichte."
        },
        {
          "Hauptstadt": "Njaswisch",
          "Bedeutende historische und architektonische Wahrzeichen": "Schloss Njaswisch (UNESCO-Welterbe), Corpus-Christi-Kirche.",
          "Wichtigste touristische Aktivitäten und Erlebnisse": "Besuch des Schlosses Njaswisch, Erkundung der umliegenden Gärten und des Palastes.",
          "Grünflächen und Landschaften": "Die ausgedehnten Schlossgärten, See Njaswisch.",
          "Berühmte lokale Gerichte": "Mittelalterliche Adelsgerichte, Met-Getränke."
        },
        {
          "Hauptstadt": "Mir",
          "Bedeutende historische und architektonische Wahrzeichen": "Schlosskomplex Mir (UNESCO-Welterbe).",
          "Wichtigste touristische Aktivitäten und Erlebnisse": "Besuch des historischen Schlosses Mir, Erkundung des umliegenden traditionellen Dorfes.",
          "Grünflächen und Landschaften": "See in der Nähe des Schlosses Mir.",
          "Berühmte lokale Gerichte": "Schaschlik (Spieß), Honigsüßigkeiten."
        },
        {
          "Hauptstadt": "Polazk",
          "Bedeutende historische und architektonische Wahrzeichen": "Sophienkathedrale, Boris-Stein.",
          "Wichtigste touristische Aktivitäten und Erlebnisse": "Besuch der Sophienkathedrale, Besuch des geografischen Zentrums Europas.",
          "Grünflächen und Landschaften": "Dwina-Fluss, alte Gärten.",
          "Berühmte lokale Gerichte": "Weißrussisches Schwarzbrot, Flussfischgerichte."
        },
        {
          "Hauptstadt": "Pinsk",
          "Bedeutende historische und architektonische Wahrzeichen": "Butrimowitsch-Palast, St. Karl Kirche.",
          "Wichtigste touristische Aktivitäten und Erlebnisse": "Flusskreuzfahrten, Erkundung der Barockarchitektur, Besuch des Regionalmuseums.",
          "Grünflächen und Landschaften": "Pripjat-Fluss, das Feuchtgebiet.",
          "Berühmte lokale Gerichte": "Gebratener Flussfisch, Pilzsuppe."
        }
      ]
    },
    {
      "Land": "Trinidad und Tobago",
      "Städte": [
        {
          "Hauptstadt": "Port of Spain",
          "Bedeutende historische und architektonische Wahrzeichen": "Die Magnificent Seven (koloniale Gebäude), das Red House (Parlament).",
          "Wichtigste touristische Aktivitäten und Erlebnisse": "Besuch des Queen's Park Savannah, Erkundung des Nationalmuseums, Teilnahme am Karneval-Festival (saisonal).",
          "Grünflächen und Landschaften": "Queen's Park Savannah, Königlicher Botanischer Garten.",
          "Berühmte lokale Gerichte": "Doubles (curry-Kichererbsen im Brot), Roti (indisches gefülltes Brot)."
        },
        {
          "Hauptstadt": "Scarborough",
          "Bedeutende historische und architektonische Wahrzeichen": "Fort König Georg, Konferenzzentrum von Tobago.",
          "Wichtigste touristische Aktivitäten und Erlebnisse": "Besuch von Fort König Georg, Spaziergang durch die Botanischen Gärten, Spaziergang an der Uferpromenade.",
          "Grünflächen und Landschaften": "Strände von Scarborough, die Botanischen Gärten.",
          "Berühmte lokale Gerichte": "Krebs und Klöße, Meeresfrüchte."
        },
        {
          "Hauptstadt": "San Fernando",
          "Bedeutende historische und architektonische Wahrzeichen": "San Fernando Hill.",
          "Wichtigste touristische Aktivitäten und Erlebnisse": "Besteigung des San Fernando Hill für einen Panoramablick, Erkundung des Zentralmarktes.",
          "Grünflächen und Landschaften": "San Fernando Hill.",
          "Berühmte lokale Gerichte": "Pelau (Gemüsesuppe), Curry."
        },
        {
          "Hauptstadt": "Arima",
          "Bedeutende historische und architektonische Wahrzeichen": "Santa Rosa Kirche.",
          "Wichtigste touristische Aktivitäten und Erlebnisse": "Besuch des Asa Wright Naturzentrums, Teilnahme am Santa Rosa Festival im August.",
          "Grünflächen und Landschaften": "Asa Wright Naturzentrum.",
          "Berühmte lokale Gerichte": "Geräuchertes Fleisch, Kaninchengerichte."
        },
        {
          "Hauptstadt": "Chaguanas",
          "Bedeutende historische und architektonische Wahrzeichen": "Der Waterloo Hindu-Tempel.",
          "Wichtigste touristische Aktivitäten und Erlebnisse": "Besuch des Waterloo-Tempels, Einkaufen im belebten Markt von Chaguanas.",
          "Grünflächen und Landschaften": "Strände von Waterloo.",
          "Berühmte lokale Gerichte": "Verschiedene kreolisch-indische Gerichte, Hühnchen-Curry."
        },
        {
          "Hauptstadt": "Maracas",
          "Bedeutende historische und architektonische Wahrzeichen": "Aussichtspunkte entlang der Küstenstraße.",
          "Wichtigste touristische Aktivitäten und Erlebnisse": "Entspannen am berühmten Maracas-Strand, Probieren des 'Shark and Bake'-Sandwiches.",
          "Grünflächen und Landschaften": "Maracas-Strand, umliegende Wälder.",
          "Berühmte lokale Gerichte": "Bake and Shark, Meeresfrüchte."
        },
        {
          "Hauptstadt": "Crown Point",
          "Bedeutende historische und architektonische Wahrzeichen": "Leuchtturm Crown Point.",
          "Wichtigste touristische Aktivitäten und Erlebnisse": "Genuss des Strandes Pigeon Point (berühmt), Schnorcheln im Nylon-Pool.",
          "Grünflächen und Landschaften": "Strand Pigeon Point, der Nylon-Pool.",
          "Berühmte lokale Gerichte": "Meeresfrüchte-Grillfeste, Curry-Gerichte."
        },
        {
          "Hauptstadt": "Charlotteville",
          "Bedeutende historische und architektonische Wahrzeichen": "Altes Fischerdorf.",
          "Wichtigste touristische Aktivitäten und Erlebnisse": "Genuss der Ruhe der Pirate's Bay, Schnorcheltouren.",
          "Grünflächen und Landschaften": "Pirate's Bay.",
          "Berühmte lokale Gerichte": "Frisch gebratener Fisch, tropische Früchte."
        },
        {
          "Hauptstadt": "Boco",
          "Bedeutende historische und architektonische Wahrzeichen": "Alte koloniale Plantagen.",
          "Wichtigste touristische Aktivitäten und Erlebnisse": "Besuch des Buccoo-Riffs, Spaziergang im geschützten Buccoo-Wald.",
          "Grünflächen und Landschaften": "Buccoo-Riff, Buccoo-Bucht.",
          "Berühmte lokale Gerichte": "Tropische Getränke, gegrillter Fisch."
        },
        {
          "Hauptstadt": "Toco",
          "Bedeutende historische und architektonische Wahrzeichen": "Leuchtturm Toco.",
          "Wichtigste touristische Aktivitäten und Erlebnisse": "Besuch des alten Leuchtturms, Beobachten von Meeresschildkröten an den Stränden (saisonal).",
          "Grünflächen und Landschaften": "Strände von Toco.",
          "Berühmte lokale Gerichte": "Brotfrucht, Hühnchengerichte."
        }
      ]
    },
    {
      "Land": "Timor-Leste",
      "Städte": [
        {
          "Hauptstadt": "Dili",
          "Bedeutende historische und architektonische Wahrzeichen": "Cristo Rei Statue, Widerstandsmuseum, Regierungspalast.",
          "Wichtigste touristische Aktivitäten und Erlebnisse": "Besteigung der Cristo Rei Statue, Besuch des Widerstandsmuseums, Tauchen in den nahegelegenen Korallenriffen.",
          "Grünflächen und Landschaften": "Strand Areia Branca, das Meer von Dili.",
          "Berühmte lokale Gerichte": "Ikan Pepes (gewürzter Fisch in Bananenblättern), Batar Dan (Maisgericht)."
        },
        {
          "Hauptstadt": "Baucau",
          "Bedeutende historische und architektonische Wahrzeichen": "Alte koloniale Gebäude, Markt von Baucau.",
          "Wichtigste touristische Aktivitäten und Erlebnisse": "Besuch alter portugiesischer Gebäude, Schwimmen im natürlichen Pool (Piscina Natural).",
          "Grünflächen und Landschaften": "Der natürliche Pool, Strand von Baucau.",
          "Berühmte lokale Gerichte": "Portugiesisch-Timoresische Gerichte, gegrillter Fisch."
        },
        {
          "Hauptstadt": "Maubisse",
          "Bedeutende historische und architektonische Wahrzeichen": "Traditionelle Häuser (Lopo), Maubisse-Schrein.",
          "Wichtigste touristische Aktivitäten und Erlebnisse": "Genuss von Bergansichten, Besuch von Blumengärten, Sehen des traditionellen Schreins.",
          "Grünflächen und Landschaften": "Umgebende Berge und Hügel, Gärten der Gegend.",
          "Berühmte lokale Gerichte": "Lokaler timoresischer Kaffee, Lamm."
        },
        {
          "Hauptstadt": "Lospalos",
          "Bedeutende historische und architektonische Wahrzeichen": "Traditionelle Häuser (Uma Lulik).",
          "Wichtigste touristische Aktivitäten und Erlebnisse": "Besuch des Ira Lalaro-Sees, Erkundung der traditionellen Häuser (Lopo).",
          "Grünflächen und Landschaften": "See Ira Lalaro, Wälder der Gegend.",
          "Berühmte lokale Gerichte": "Gekochtes Büffelfleisch, Fisch aus dem See."
        },
        {
          "Hauptstadt": "Viqueque",
          "Bedeutende historische und architektonische Wahrzeichen": "Der zentrale Markt.",
          "Wichtigste touristische Aktivitäten und Erlebnisse": "Entspannen in den Thermalquellen, Erkundung ländlicher Dörfer.",
          "Grünflächen und Landschaften": "Thermalquellen, ländliche Natur.",
          "Berühmte lokale Gerichte": "Reis und Gemüse, Schweinefleisch."
        },
        {
          "Hauptstadt": "Maliana",
          "Bedeutende historische und architektonische Wahrzeichen": "Grenzorte mit Indonesien.",
          "Wichtigste touristische Aktivitäten und Erlebnisse": "Durchschlendern traditioneller Märkte, Erkundung der Grenzlandschaften mit Indonesien.",
          "Grünflächen und Landschaften": "Hügel von Maliana, Ackerland.",
          "Berühmte lokale Gerichte": "Tapai (fermentierter Maniok), gekochtes Hühnchen."
        },
        {
          "Hauptstadt": "Atauro (Insel)",
          "Bedeutende historische und architektonische Wahrzeichen": "Traditionelle Insel-Dörfer.",
          "Wichtigste touristische Aktivitäten und Erlebnisse": "Tauchen und Schnorcheln in den Gewässern mit hoher Biodiversität, Besuch von Dörfern zur Puppenherstellung.",
          "Grünflächen und Landschaften": "Korallenriffe, Inselstrände.",
          "Berühmte lokale Gerichte": "Frisch gegrillter Fisch, Meeresfrüchte."
        },
        {
          "Hauptstadt": "Jaco (Insel)",
          "Bedeutende historische und architektonische Wahrzeichen": "Eine heilige Insel nur für Besuche.",
          "Wichtigste touristische Aktivitäten und Erlebnisse": "Tauchen und Schnorcheln in den Gewässern mit hoher Biodiversität, Vogelbeobachtung.",
          "Grünflächen und Landschaften": "Weiße Sandstrände, klares Wasser.",
          "Berühmte lokale Gerichte": "Essen muss mitgebracht werden (unbewohnte Insel)."
        },
        {
          "Hauptstadt": "Balibo",
          "Bedeutende historische und architektonische Wahrzeichen": "Balibo-Festung, das Journalisten-Denkmal.",
          "Wichtigste touristische Aktivitäten und Erlebnisse": "Besuch der historischen Festung, Besuch des Journalisten-Denkmals, Blick auf die Küste.",
          "Grünflächen und Landschaften": "Strand von Balibo.",
          "Berühmte lokale Gerichte": "Kaffee und frittierte Bananen."
        },
        {
          "Hauptstadt": "Liquiçá",
          "Bedeutende historische und architektonische Wahrzeichen": "Koloniale Häuser, Stadtzentrum.",
          "Wichtigste touristische Aktivitäten und Erlebnisse": "Entspannen an schwarzen Sandstränden, Erkundung alter kolonialer Gebäude.",
          "Grünflächen und Landschaften": "Schwarze Sandstrände, der Ozean.",
          "Berühmte lokale Gerichte": "Kaffee und frittierte Bananen."
        }
      ]
    },
    {
      "Land": "Tuvalu",
      "Städte": [
        {
          "Hauptstadt": "Funafuti",
          "Bedeutende historische und architektonische Wahrzeichen": "Regierungsgebäude (Vai Fenua), Flughafen Funafuti International.",
          "Wichtigste touristische Aktivitäten und Erlebnisse": "Besuch des Naturschutzgebiets Funafuti, Fußballspielen auf der Landebahn bei Dämmerung, Besuch des Regierungsgebäudes.",
          "Grünflächen und Landschaften": "Naturschutzgebiet Funafuti, die Lagune.",
          "Berühmte lokale Gerichte": "Pulu Sami (Taro-Paste mit Kokosnuss), frischer Thunfisch."
        },
        {
          "Hauptstadt": "Vaitupu",
          "Bedeutende historische und architektonische Wahrzeichen": "Kirche von Vaitupu.",
          "Wichtigste touristische Aktivitäten und Erlebnisse": "Entspannen an ruhigen Stränden, Besuch lokaler Schulen, Erleben des Dorflebens.",
          "Grünflächen und Landschaften": "Inselstrände, kleine Wälder.",
          "Berühmte lokale Gerichte": "Gebratene Brotfrucht, Kokosnuss-Suppe."
        },
        {
          "Hauptstadt": "Nanumanga",
          "Bedeutende historische und architektonische Wahrzeichen": "Die große Kirche von Nanumanga, historische Gebäude.",
          "Wichtigste touristische Aktivitäten und Erlebnisse": "Sehen von Flugzeugwracks aus dem Zweiten Weltkrieg, Besuch der großen Kirche.",
          "Grünflächen und Landschaften": "Strand von Nanumanga, Überreste aus dem Zweiten Weltkrieg.",
          "Berühmte lokale Gerichte": "Kokosnusskrebs, gekochter Fisch."
        },
        {
          "Hauptstadt": "Niutao",
          "Bedeutende historische und architektonische Wahrzeichen": "Dorfzentrum.",
          "Wichtigste touristische Aktivitäten und Erlebnisse": "Erkundung der lokalen Kultur, Erlernen traditioneller Handwerke.",
          "Grünflächen und Landschaften": "Die Lagune, Bäume.",
          "Berühmte lokale Gerichte": "Tuvalu-Pudding, Taro-Gerichte."
        },
        {
          "Hauptstadt": "Nui",
          "Bedeutende historische und architektonische Wahrzeichen": "Dorfzentrum.",
          "Wichtigste touristische Aktivitäten und Erlebnisse": "Schnorcheln um die Korallenriffe, Genuss vollständiger Ruhe.",
          "Grünflächen und Landschaften": "Korallenriffe, das Meer.",
          "Berühmte lokale Gerichte": "Gesalzener und getrockneter Fisch, Kokosnuss-Gerichte."
        },
        {
          "Hauptstadt": "Nukufetau",
          "Bedeutende historische und architektonische Wahrzeichen": "Kleine historische Spuren.",
          "Wichtigste touristische Aktivitäten und Erlebnisse": "Entspannen an der großen Lagune, Schnorcheln.",
          "Grünflächen und Landschaften": "Die Lagune.",
          "Berühmte lokale Gerichte": "Frische Kokosnussmilch, Fisch."
        },
        {
          "Hauptstadt": "Nukulaelae",
          "Bedeutende historische und architektonische Wahrzeichen": "Tefala (alte religiöse Stätte).",
          "Wichtigste touristische Aktivitäten und Erlebnisse": "Besuch der alten Stätte (Tefala), Genuss der Natur.",
          "Grünflächen und Landschaften": "Strände, Natur.",
          "Berühmte lokale Gerichte": "Traditionelle Meeresfrüchte-Gerichte, Früchte."
        },
        {
          "Hauptstadt": "Niulakita",
          "Bedeutende historische und architektonische Wahrzeichen": "Keine bedeutenden architektonischen Wahrzeichen.",
          "Wichtigste touristische Aktivitäten und Erlebnisse": "Genuss vollständiger Isolation, Erkundung der Insel.",
          "Grünflächen und Landschaften": "Unerforschte Strände.",
          "Berühmte lokale Gerichte": "Traditionelle Seevogel-Gerichte, Früchte."
        },
        {
          "Hauptstadt": "Amatuku (Eiland)",
          "Bedeutende historische und architektonische Wahrzeichen": "Das Maritime Trainingsinstitut.",
          "Wichtigste touristische Aktivitäten und Erlebnisse": "Besuch des Maritimen Instituts, Entspannen an kleinen Stränden.",
          "Grünflächen und Landschaften": "Strände des Eilands.",
          "Berühmte lokale Gerichte": "Lokale Gerichte aus Taro und Fisch."
        },
        {
          "Hauptstadt": "Tepuka (Eiland)",
          "Bedeutende historische und architektonische Wahrzeichen": "Keine bedeutenden architektonischen Wahrzeichen.",
          "Wichtigste touristische Aktivitäten und Erlebnisse": "Ausflüge zu unbewohnten Eilanden, Vogelbeobachtung.",
          "Grünflächen und Landschaften": "Strände, das Meer.",
          "Berühmte lokale Gerichte": "Strandgrillfest."
        }
      ]
    },
    {
      "Land": "San Marino",
      "Städte": [
        {
          "Hauptstadt": "Stadt San Marino (Hauptstadt)",
          "Bedeutende historische und architektonische Wahrzeichen": "Die drei Türme (Guaita, Cesta, Montale), Palazzo Pubblico (Regierungspalast), Kirche San Antonio.",
          "Wichtigste touristische Aktivitäten und Erlebnisse": "Erkundung der drei Festungen, Besuch von Museen, Spaziergang durch die alten Stadtstraßen, Kauf von Gedenk-Briefmarken, Genuss von Cafés und Restaurants.",
          "Grünflächen und Landschaften": "Parco Guido, Stadtparks, Piazza San Marco, Panoramablick auf die Alpen.",
          "Berühmte lokale Gerichte": "Neapolitanische Pizza, Spaghetti, Pasta, Lasagne, Schnecken, Nudzli (lokale Nudeln mit Fleisch), Torta Tre Monti (Kuchen der drei Türme)."
        },
        {
          "Hauptstadt": "Borgo Maggiore",
          "Bedeutende historische und architektonische Wahrzeichen": "Kirche San Francesco, Kirche Santa Chiara, Teatro San Carlo.",
          "Wichtigste touristische Aktivitäten und Erlebnisse": "Besuch historischer Kirchen, Spaziergang durch die Altstadt, Einkaufen in kommerziellen Straßen, Genuss der Landschaften.",
          "Grünflächen und Landschaften": "Stadtparks, Ausblicke auf die umliegenden Berge.",
          "Berühmte lokale Gerichte": "Spaghetti, Lasagna, lokale Pasta, lokale Kuchen."
        },
        {
          "Hauptstadt": "Serravalle",
          "Bedeutende historische und architektonische Wahrzeichen": "Kirche Santa Maria Assunta, Museum Serravalle.",
          "Wichtigste touristische Aktivitäten und Erlebnisse": "Besuch des Museums, Spaziergang durch die Stadt, Genuss der nahegelegenen Strände in Rimini, Italien.",
          "Grünflächen und Landschaften": "Stadtparks, Küstenansichten.",
          "Berühmte lokale Gerichte": "Frische Meeresfrüchte, lokale Pasta, Fleischgerichte."
        }
      ]
    },
    {
      "Land": "Liechtenstein",
      "Städte": [
        {
          "Hauptstadt": "Vaduz (Hauptstadt)",
          "Bedeutende historische und architektonische Wahrzeichen": "Schloss Vaduz (Residenz des Fürsten), St. Florin Kathedrale, Kunstmuseum.",
          "Wichtigste touristische Aktivitäten und Erlebnisse": "Besuch des Schlosses (von außen), Spaziergang durch die Altstadt, Besuch des Kunstmuseums, Kauf von Gedenk-Briefmarken, Wandern in den Alpen.",
          "Grünflächen und Landschaften": "Stadtparks, Alpenansichten, das Rheintal.",
          "Berühmte lokale Gerichte": "Käsefondue, Schweizer Schokolade, Rösti (Gericht aus geriebenen Kartoffeln und Käse), Käsknöpfle (Schichten aus Kartoffeln, Fleisch und Käse), Knödel (Klöße)."
        }
      ]
    },
    {
      "Land": "Nordmazedonien",
      "Städte": [
        {
          "Hauptstadt": "Skopje (Hauptstadt)",
          "Bedeutende historische und architektonische Wahrzeichen": "Kale-Festung, Marschall-Tito-Platz, St. Clemens Kirche, Steinbrücke, Nationalmuseum.",
          "Wichtigste touristische Aktivitäten und Erlebnisse": "Besuch der Festung, Spaziergang durch die Altstadt (der alte Basar), Besuch des Basar-Marktes, Genuss des lebhaften Nachtlebens.",
          "Grünflächen und Landschaften": "Stadtparks, Ausblicke auf das Šar-Gebirge, Vardar-Fluss.",
          "Berühmte lokale Gerichte": "Ajvar (geröstete Paprika-Aufstrich), Pastrmajlija (lokaler Kuchen), Kavapi (Hackfleischgericht), Turšija (eingelegtes Gemüse)."
        },
        {
          "Hauptstadt": "Ohrid",
          "Bedeutende historische und architektonische Wahrzeichen": "Ohrid-See, Kirche St. Georg, Samuel-Festung, Kirche St. Sophia (UNESCO-Welterbe).",
          "Wichtigste touristische Aktivitäten und Erlebnisse": "Entspannen am See, Besuch alter Kirchen und Klöster, Erkundung der Natur, Spaziergang in der Altstadt.",
          "Grünflächen und Landschaften": "Ohrid-See, Stadtparks, umliegende Berge.",
          "Berühmte lokale Gerichte": "Frische Fischgerichte (besonders Forelle), Lamm-Suppe, Ohrid Turšija (lokales Einlegemittel)."
        },
        {
          "Hauptstadt": "Bitola",
          "Bedeutende historische und architektonische Wahrzeichen": "St. Nikolaus-Friedhof, Kirche St. Johannes.",
          "Wichtigste touristische Aktivitäten und Erlebnisse": "Besuch des Friedhofs, Spaziergang durch die Stadt, Genuss der Bergnatur.",
          "Grünflächen und Landschaften": "Stadtparks, Ausblicke auf die umliegenden Berge.",
          "Berühmte lokale Gerichte": "Gegrillte Fleischgerichte, lokales Brot, Milchprodukte."
        }
      ]
    },
    {
      "Land": "Albanien",
      "Städte": [
        {
          "Hauptstadt": "Tirana (Hauptstadt)",
          "Bedeutende historische und architektonische Wahrzeichen": "Et'hem Bey Moschee, Opernhaus, Nationalhistorisches Museum, Pyramide von Tirana, Skanderbeg-Platz.",
          "Wichtigste touristische Aktivitäten und Erlebnisse": "Besuch der Moschee und des Palastes, Spaziergang durch die Altstadt, Erkundung des Block-Bereichs (ehemalige kommunistische Partei), Genuss des Nachtlebens.",
          "Grünflächen und Landschaften": "Großer Park, der künstliche See von Tirana.",
          "Berühmte lokale Gerichte": "Tavë Kosi (nationaler Eintopf mit Aubergine und Hackfleisch), Byrek (herzhafte Kuchen mit verschiedenen Füllungen), Pita (Fladenbrot), Raki (gegrilltes Fleisch)."
        },
        {
          "Hauptstadt": "Durres",
          "Bedeutende historische und architektonische Wahrzeichen": "St. Paulus Kathedrale, Rozafa Festung.",
          "Wichtigste touristische Aktivitäten und Erlebnisse": "Besuch der Kathedrale, Spaziergang durch die Stadt, Genuss der Strände, Besuch der Rozafa Festung.",
          "Grünflächen und Landschaften": "Strände von Durres, Stadtparks.",
          "Berühmte lokale Gerichte": "Gegrillte Fischgerichte, Meeresfrüchte, Durres Pita (lokaler Pita)."
        },
        {
          "Hauptstadt": "Vlore",
          "Bedeutende historische und architektonische Wahrzeichen": "Vlore Moschee, Vlore Museum.",
          "Wichtigste touristische Aktivitäten und Erlebnisse": "Besuch der Moschee, Spaziergang durch die Stadt, Genuss der Natur.",
          "Grünflächen und Landschaften": "Stadtparks, Bergansichten.",
          "Berühmte lokale Gerichte": "Gegrillte Fleischgerichte, lokales Brot, lokaler Käse."
        }
      ]
    },
    {
      "Land": "Kroatien",
      "Städte": [
        {
          "Hauptstadt": "Zagreb (Hauptstadt)",
          "Bedeutende historische und architektonische Wahrzeichen": "Gornji Grad (Oberstadt), St. Stephans Kathedrale, Steinernes Tor, Dolac Markt.",
          "Wichtigste touristische Aktivitäten und Erlebnisse": "Besuch der Altstadt, Spaziergang durch die Straßen, Fahrt mit der Standseilbahn, Genuss des Nachtlebens.",
          "Grünflächen und Landschaften": "Stadtparks, Medvednica-Berg.",
          "Berühmte lokale Gerichte": "Pašticada (marinierter Rindfleischeintopf), Pžolice (frittierte Muscheln), Ražnjići (gegrilltes Fleisch), Šopska Salata (kroatische Version)."
        },
        {
          "Hauptstadt": "Split",
          "Bedeutende historische und architektonische Wahrzeichen": "Diokletianspalast (UNESCO-Welterbe), Kathedrale des Heiligen Domnius, Diokletians Mausoleum.",
          "Wichtigste touristische Aktivitäten und Erlebnisse": "Besuch des Palastes, Spaziergang durch die Stadt, Genuss der Strände.",
          "Grünflächen und Landschaften": "Strände von Split, Stadtparks, Marjan-Hügel.",
          "Berühmte lokale Gerichte": "Pašticada, Pžolice, Ražnjići, Pečenica (Holzkohle-gegrilltes Fleisch)."
        },
        {
          "Hauptstadt": "Dubrovnik",
          "Bedeutende historische und architektonische Wahrzeichen": "Dubrovnik-Mauern, St. Tryphon Kathedrale, Stradun Straße.",
          "Wichtigste touristische Aktivitäten und Erlebnisse": "Spaziergang auf den Mauern, Erkundung der Altstadt, Genuss der Natur.",
          "Grünflächen und Landschaften": "Stadtparks, Insel Lokrum.",
          "Berühmte lokale Gerichte": "Pašticada, Pžolice, Ražnjići, frische Meeresfrüchte."
        }
      ]
    },
    {
      "Land": "Serbien",
      "Städte": [
        {
          "Hauptstadt": "Belgrad (Hauptstadt)",
          "Bedeutende historische und architektonische Wahrzeichen": "Belgrader Festung, St. Michael Kathedrale, Nikola Tesla Museum, Tempel des Heiligen Sava.",
          "Wichtigste touristische Aktivitäten und Erlebnisse": "Besuch der Festung, Spaziergang durch die Stadt, Genuss des Nachtlebens.",
          "Grünflächen und Landschaften": "Stadtparks, Ausblicke auf die Flüsse Save und Donau.",
          "Berühmte lokale Gerichte": "Karađorđeva (Steak), Šopska Salata, Sarma (Kohlrouladen), Gibanica (Kuchen mit Käse und Spinat)."
        },
        {
          "Hauptstadt": "Novi Sad",
          "Bedeutende historische und architektonische Wahrzeichen": "Petrovaradin Festung, St. Georg Kirche.",
          "Wichtigste touristische Aktivitäten und Erlebnisse": "Besuch der Festung, Spaziergang durch die Stadt, Genuss der Natur.",
          "Grünflächen und Landschaften": "Stadtparks, Bergansichten.",
          "Berühmte lokale Gerichte": "Karađorđeva, Šopska Salata, Sarma."
        },
        {
          "Hauptstadt": "Niš",
          "Bedeutende historische und architektonische Wahrzeichen": "Niš Festung, St. Tryphon Kathedrale.",
          "Wichtigste touristische Aktivitäten und Erlebnisse": "Besuch der Festung, Spaziergang durch die Stadt, Genuss der Natur.",
          "Grünflächen und Landschaften": "Stadtparks, Bergansichten.",
          "Berühmte lokale Gerichte": "Karađorđeva, Šopska Salata, Sarma."
        }
      ]
    },
    {
      "Land": "Montenegro",
      "Städte": [
        {
          "Hauptstadt": "Podgorica (Hauptstadt)",
          "Bedeutende historische und architektonische Wahrzeichen": "Millenniumsbrücke, Podgorica Palast, St. Andreas Kirche.",
          "Wichtigste touristische Aktivitäten und Erlebnisse": "Besuch des Palastes, Spaziergang durch die Stadt, Genuss des Nachtlebens.",
          "Grünflächen und Landschaften": "Stadtparks, Bergansichten.",
          "Berühmte lokale Gerichte": "Karađorđeva, Šopska Salata, Sarma."
        },
        {
          "Hauptstadt": "Kotor",
          "Bedeutende historische und architektonische Wahrzeichen": "St. Nikolaus Kirche, Kotor Museum.",
          "Wichtigste touristische Aktivitäten und Erlebnisse": "Besuch der Kirche, Spaziergang durch die Stadt, Genuss der Natur.",
          "Grünflächen und Landschaften": "Stadtparks, Bergansichten.",
          "Berühmte lokale Gerichte": "Karađorđeva, Šopska Salata, Sarma."
        },
        {
          "Hauptstadt": "Nikšić",
          "Bedeutende historische und architektonische Wahrzeichen": "Nikšić Museum, St. Stephan Kirche.",
          "Wichtigste touristische Aktivitäten und Erlebnisse": "Besuch des Museums, Spaziergang durch die Stadt, Genuss der Natur.",
          "Grünflächen und Landschaften": "Stadtparks, Bergansichten.",
          "Berühmte lokale Gerichte": "Karađorđeva, Šopska Salata, Sarma."
        }
      ]
    },
    {
      "Land": "Kosovo",
      "Städte": [
        {
          "Hauptstadt": "Pristina (Hauptstadt)",
          "Bedeutende historische und architektonische Wahrzeichen": "Mutter Teresa Kathedrale, Kosovo Museum.",
          "Wichtigste touristische Aktivitäten und Erlebnisse": "Besuch der Kathedrale, Spaziergang durch die Stadt, Genuss des Nachtlebens.",
          "Grünflächen und Landschaften": "Stadtparks, Bergansichten.",
          "Berühmte lokale Gerichte": "Karađorđeva, Šopska Salata, Sarma."
        },
        {
          "Hauptstadt": "Prizren",
          "Bedeutende historische und architektonische Wahrzeichen": "St. Nikolaus Kirche, Prizren Museum.",
          "Wichtigste touristische Aktivitäten und Erlebnisse": "Besuch der Kirche, Spaziergang durch die Stadt, Genuss der Natur.",
          "Grünflächen und Landschaften": "Stadtparks, Bergansichten.",
          "Berühmte lokale Gerichte": "Karađorđeva, Šopska Salata, Sarma."
        },
        {
          "Hauptstadt": "Pristina",
          "Bedeutende historische und architektonische Wahrzeichen": "Mutter Teresa Kathedrale, Kosovo Museum.",
          "Wichtigste touristische Aktivitäten und Erlebnisse": "Besuch der Kathedrale, Spaziergang durch die Stadt, Genuss des Nachtlebens.",
          "Grünflächen und Landschaften": "Stadtparks, Bergansichten.",
          "Berühmte lokale Gerichte": "Karađorđeva, Šopska Salata, Sarma."
        }
      ]
    }
  ]
}